LICENSE
MANIFEST.in
README.md
bower.json
gulpfile.js
karma.conf.js
package.json
setup.py
django_querybuilder/__init__.py
django_querybuilder/endpoint.py
django_querybuilder/filterform.py
django_querybuilder/map.py
django_querybuilder/table.py
django_querybuilder/widget.py
django_querybuilder.egg-info/PKG-INFO
django_querybuilder.egg-info/SOURCES.txt
django_querybuilder.egg-info/dependency_links.txt
django_querybuilder.egg-info/not-zip-safe
django_querybuilder.egg-info/top_level.txt
django_querybuilder/static/django_querybuilder/dist/querybuilder-no-datatables.css
django_querybuilder/static/django_querybuilder/dist/querybuilder.css
django_querybuilder/static/django_querybuilder/dist/querybuilder.js
django_querybuilder/static/django_querybuilder/dist/querybuilder.js.map
django_querybuilder/static/django_querybuilder/dist/images/br_down.png
django_querybuilder/static/django_querybuilder/dist/images/layers-2x.png
django_querybuilder/static/django_querybuilder/dist/images/layers.png
django_querybuilder/static/django_querybuilder/dist/images/marker-icon-2x.png
django_querybuilder/static/django_querybuilder/dist/images/marker-icon.png
django_querybuilder/static/django_querybuilder/dist/images/marker-shadow.png
django_querybuilder/static/django_querybuilder/dist/images/sort_asc.png
django_querybuilder/static/django_querybuilder/dist/images/sort_asc_disabled.png
django_querybuilder/static/django_querybuilder/dist/images/sort_both.png
django_querybuilder/static/django_querybuilder/dist/images/sort_desc.png
django_querybuilder/static/django_querybuilder/dist/images/sort_desc_disabled.png
django_querybuilder/templates/django_querybuilder/css_assets.html
django_querybuilder/templates/django_querybuilder/datatable_template.html
django_querybuilder/templates/django_querybuilder/filterform_template.html
django_querybuilder/templates/django_querybuilder/js_assets.html
django_querybuilder/templates/django_querybuilder/map_widget.html
django_querybuilder/templates/django_querybuilder/table_widget.html